py_taliro-0.2.1.dist-info/WHEEL
py_taliro-0.2.1.dist-info/RECORD
py_taliro-0.2.1.dist-info/METADATA
py_taliro-0.2.1.dist-info/top_level.txt
py_taliro-0.2.1.dist-info/LICENSE.txt
taliro/tptaliro.cpython-38-x86_64-linux-gnu.so
